{
  "session_id": "20260601_171613_047476",
  "session_user": [
    "DANIELA STEIM"
  ],
  "mouse_movements": [
    {
      "x": 486,
      "y": 189,
      "time_offset": 0.10264945030212402
    },
    {
      "x": 488,
      "y": 189,
      "time_offset": 0.1108846664428711
    },
    {
      "x": 489,
      "y": 186,
      "time_offset": 0.11992669105529785
    },
    {
      "x": 491,
      "y": 186,
      "time_offset": 0.12502646446228027
    },
    {
      "x": 494,
      "y": 185,
      "time_offset": 0.13269615173339844
    },
    {
      "x": 476,
      "y": 189,
      "time_offset": 0.3733797073364258
    },
    {
      "x": 453,
      "y": 193,
      "time_offset": 0.37746310234069824
    },
    {
      "x": 222,
      "y": 57,
      "time_offset": 0.4168517589569092
    },
    {
      "x": 213,
      "y": 171,
      "time_offset": 0.43077778816223145
    },
    {
      "x": 194,
      "y": 175,
      "time_offset": 0.43894100189208984
    },
    {
      "x": 181,
      "y": 177,
      "time_offset": 0.44701457023620605
    },
    {
      "x": 169,
      "y": 180,
      "time_offset": 0.45493173599243164
    },
    {
      "x": 159,
      "y": 181,
      "time_offset": 0.46286606788635254
    },
    {
      "x": 152,
      "y": 182,
      "time_offset": 0.47066307067871094
    },
    {
      "x": 147,
      "y": 182,
      "time_offset": 0.47879552841186523
    },
    {
      "x": 142,
      "y": 182,
      "time_offset": 0.4868321418762207
    },
    {
      "x": 136,
      "y": 182,
      "time_offset": 0.49556684494018555
    },
    {
      "x": 132,
      "y": 182,
      "time_offset": 0.5009188652038574
    },
    {
      "x": 130,
      "y": 182,
      "time_offset": 0.509735107421875
    },
    {
      "x": 129,
      "y": 182,
      "time_offset": 0.5175037384033203
    },
    {
      "x": 128,
      "y": 182,
      "time_offset": 0.5253767967224121
    },
    {
      "x": 127,
      "y": 182,
      "time_offset": 0.5416145324707031
    },
    {
      "x": 126,
      "y": 181,
      "time_offset": 0.5497574806213379
    },
    {
      "x": 125,
      "y": 180,
      "time_offset": 0.5575318336486816
    },
    {
      "x": 123,
      "y": 179,
      "time_offset": 0.5655601024627686
    },
    {
      "x": 123,
      "y": 178,
      "time_offset": 0.5735549926757812
    },
    {
      "x": 122,
      "y": 177,
      "time_offset": 0.5794517993927002
    },
    {
      "x": 119,
      "y": 175,
      "time_offset": 0.5881938934326172
    },
    {
      "x": 118,
      "y": 174,
      "time_offset": 0.595449686050415
    },
    {
      "x": 116,
      "y": 172,
      "time_offset": 0.6036956310272217
    },
    {
      "x": 113,
      "y": 171,
      "time_offset": 0.6113271713256836
    },
    {
      "x": 111,
      "y": 169,
      "time_offset": 0.6196708679199219
    },
    {
      "x": 108,
      "y": 169,
      "time_offset": 0.6281201839447021
    },
    {
      "x": 107,
      "y": 167,
      "time_offset": 0.6356635093688965
    },
    {
      "x": 104,
      "y": 166,
      "time_offset": 0.6432111263275146
    },
    {
      "x": 103,
      "y": 165,
      "time_offset": 0.6515183448791504
    },
    {
      "x": 102,
      "y": 163,
      "time_offset": 0.6575188636779785
    },
    {
      "x": 100,
      "y": 163,
      "time_offset": 0.6656813621520996
    },
    {
      "x": 54,
      "y": 60,
      "time_offset": 0.681544303894043
    },
    {
      "x": 52,
      "y": 58,
      "time_offset": 0.6896817684173584
    },
    {
      "x": 50,
      "y": 58,
      "time_offset": 0.6974546909332275
    },
    {
      "x": 49,
      "y": 58,
      "time_offset": 0.7057721614837646
    },
    {
      "x": 48,
      "y": 56,
      "time_offset": 0.7135741710662842
    },
    {
      "x": 47,
      "y": 56,
      "time_offset": 0.7217006683349609
    },
    {
      "x": 46,
      "y": 56,
      "time_offset": 0.7295186519622803
    },
    {
      "x": 46,
      "y": 54,
      "time_offset": 0.7638964653015137
    },
    {
      "x": 46,
      "y": 53,
      "time_offset": 0.7855446338653564
    },
    {
      "x": 45,
      "y": 52,
      "time_offset": 0.793053150177002
    },
    {
      "x": 44,
      "y": 51,
      "time_offset": 0.8015596866607666
    },
    {
      "x": 42,
      "y": 48,
      "time_offset": 0.8099193572998047
    },
    {
      "x": 41,
      "y": 47,
      "time_offset": 0.8175029754638672
    },
    {
      "x": 41,
      "y": 46,
      "time_offset": 0.8254468441009521
    },
    {
      "x": 27,
      "y": 26,
      "time_offset": 0.8495397567749023
    },
    {
      "x": 26,
      "y": 24,
      "time_offset": 0.8575015068054199
    },
    {
      "x": 26,
      "y": 22,
      "time_offset": 0.863591194152832
    },
    {
      "x": 25,
      "y": 21,
      "time_offset": 0.8719217777252197
    },
    {
      "x": 25,
      "y": 19,
      "time_offset": 0.8796653747558594
    },
    {
      "x": 24,
      "y": 18,
      "time_offset": 0.8877997398376465
    },
    {
      "x": 24,
      "y": 17,
      "time_offset": 0.8968789577484131
    },
    {
      "x": 23,
      "y": 16,
      "time_offset": 0.9037165641784668
    },
    {
      "x": 22,
      "y": 16,
      "time_offset": 0.9117050170898438
    },
    {
      "x": 22,
      "y": 15,
      "time_offset": 0.927363395690918
    },
    {
      "x": 21,
      "y": 15,
      "time_offset": 0.9418261051177979
    },
    {
      "x": 20,
      "y": 15,
      "time_offset": 0.9574322700500488
    },
    {
      "x": 19,
      "y": 15,
      "time_offset": 1.0016608238220215
    },
    {
      "x": 18,
      "y": 15,
      "time_offset": 1.0299968719482422
    }
  ],
  "timestamps": [
    1780344973.1501212,
    1780344973.1583564,
    1780344973.1673985,
    1780344973.1724982,
    1780344973.180168,
    1780344973.4208515,
    1780344973.4249349,
    1780344973.4643235,
    1780344973.4782495,
    1780344973.4864128,
    1780344973.4944863,
    1780344973.5024035,
    1780344973.5103378,
    1780344973.5181348,
    1780344973.5262673,
    1780344973.534304,
    1780344973.5430386,
    1780344973.5483906,
    1780344973.5572069,
    1780344973.5649755,
    1780344973.5728486,
    1780344973.5890863,
    1780344973.5972292,
    1780344973.6050036,
    1780344973.6130319,
    1780344973.6210268,
    1780344973.6269236,
    1780344973.6356657,
    1780344973.6429214,
    1780344973.6511674,
    1780344973.658799,
    1780344973.6671426,
    1780344973.675592,
    1780344973.6831353,
    1780344973.690683,
    1780344973.69899,
    1780344973.7049906,
    1780344973.7131531,
    1780344973.729016,
    1780344973.7371535,
    1780344973.7449265,
    1780344973.753244,
    1780344973.761046,
    1780344973.7691724,
    1780344973.7769904,
    1780344973.8113682,
    1780344973.8330164,
    1780344973.840525,
    1780344973.8490314,
    1780344973.857391,
    1780344973.8649747,
    1780344973.8729186,
    1780344973.8970115,
    1780344973.9049733,
    1780344973.911063,
    1780344973.9193935,
    1780344973.9271371,
    1780344973.9352715,
    1780344973.9443507,
    1780344973.9511883,
    1780344973.9591768,
    1780344973.9748352,
    1780344973.9892979,
    1780344974.004904,
    1780344974.0491326,
    1780344974.0774686
  ],
  "velocities": [
    126.3344578313253,
    242.85944240178338,
    349.73114935147987,
    392.1742870500234,
    412.30855292843654,
    76.61133669222662,
    5717.114076750194,
    6805.55223565612,
    8211.580604151777,
    2378.5347880735208,
    1629.1366936345316,
    1562.3415320219221,
    1266.6316150476225,
    906.8956367176899,
    614.8202873057754,
    622.1526047229145,
    686.915165411071,
    747.3813257305774,
    226.8540213099681,
    128.72280874048613,
    127.01544424928835,
    61.58494112119343,
    173.67340872271834,
    181.9075564743536,
    278.52430321917495,
    125.07989145021322,
    239.8270165978944,
    412.4356543181529,
    194.9082115307634,
    343.00824619879273,
    414.36951604720156,
    338.9896903369369,
    355.0583255735207,
    296.4300029172628,
    418.9769668368726,
    170.23911837429964,
    372.64577488474566,
    245.0230167075593,
    7111.2372195452,
    347.5808855009067,
    257.30347831421386,
    120.22885971449865,
    286.60154205779486,
    123.05424673610092,
    127.91021926748193,
    58.1770568204673,
    46.193284067005145,
    188.34793768506407,
    166.25022005985937,
    431.3030298857403,
    186.4826962247146,
    125.88324979741289,
    1013.2901555677581,
    280.8513164729975,
    328.42408581943465,
    169.761643957406,
    258.27790264478585,
    173.85666221688618,
    110.1416454399832,
    206.8287458250191,
    125.18068405658688,
    63.863572690176014,
    69.14333756449778,
    64.0772415478864,
    22.60982814757315,
    35.290736222128736
  ],
  "accelerations": [
    14149.596389328932,
    14149.596389328932,
    14149.596389328932,
    14149.596389328932,
    11819.444375634535,
    8322.553633546138,
    2625.1742954674232,
    -1394.7659007908867,
    1381326.747511887,
    27633.289693306426,
    100964.05427315197,
    -714552.6270790705,
    -92821.17429341257,
    -8436.75169489609,
    -37269.66818729445,
    -46137.72598395105,
    -35914.77004807358,
    912.3640759456507,
    7414.397514591598,
    11297.81976535757,
    -59041.856104726576,
    -12631.725307053415,
    -216.86165934494613,
    -4029.533682673789,
    13765.096563065712,
    1059.14250647923,
    12034.56797252372,
    -19192.810367703554,
    19459.19726662434,
    19744.54140302264,
    -29979.831873062758,
    17960.3471869616,
    9350.834439384564,
    -9034.344053487986,
    1901.7675737843676,
    -7772.211771245393,
    16236.510754521107,
    -29942.37444416277,
    33731.52610570525,
    -15635.25660455676,
    432846.2093939749,
    -831174.9089246526,
    -11614.345441162326,
    -16480.32509004357,
    21324.33709336318,
    -20125.18923153769,
    621.1285112458147,
    -2028.4350769754233,
    -553.5698189951137,
    18932.455856502675,
    -2597.733832962427,
    31706.130692294784,
    -32282.78749860962,
    -7628.455252192962,
    36832.6950659573,
    -91994.70421544323,
    7812.021641251224,
    -19045.777583688916,
    11430.896821869892,
    -10378.344170575692,
    -7017.676787044226,
    14140.489274150337,
    -10220.7602240668,
    -3915.9297989003985,
    365.0605649664084
  ],
  "click_data": {
    "time_to_click": 1.1235606670379639,
    "click_position": [
      18,
      15
    ],
    "click_timestamp": 1780344974.1710324
  },
  "total_time": 1.1235606670379639,
  "distance_traveled": 734.5607265681127,
  "window_origin": {
    "x": 354,
    "y": 416
  },
  "metrics": {
    "total_time": 1.1235606670379639,
    "num_movements": 66,
    "total_distance": 734.5607265681127,
    "avg_velocity": 762.9166847112118,
    "max_velocity": 8211.580604151777,
    "avg_acceleration": 2140.0916212537613,
    "max_acceleration": 1381326.747511887,
    "time_to_click": 1.1235606670379639
  }
}