{
  "session_id": "20260129_224051_306372",
  "session_user": [
    "CELIA STEIM"
  ],
  "mouse_movements": [
    {
      "x": 143,
      "y": 225,
      "time_offset": 0.3059806823730469
    },
    {
      "x": 140,
      "y": 219,
      "time_offset": 0.31327342987060547
    },
    {
      "x": 137,
      "y": 214,
      "time_offset": 0.3193700313568115
    },
    {
      "x": 129,
      "y": 11,
      "time_offset": 0.3258216381072998
    },
    {
      "x": 125,
      "y": 3,
      "time_offset": 0.3329629898071289
    },
    {
      "x": 126,
      "y": 191,
      "time_offset": 0.33966660499572754
    },
    {
      "x": 123,
      "y": 183,
      "time_offset": 0.34591054916381836
    },
    {
      "x": 119,
      "y": 176,
      "time_offset": 0.35309767723083496
    },
    {
      "x": 116,
      "y": 169,
      "time_offset": 0.35992860794067383
    },
    {
      "x": 114,
      "y": 163,
      "time_offset": 0.36638689041137695
    },
    {
      "x": 112,
      "y": 156,
      "time_offset": 0.3732786178588867
    },
    {
      "x": 69,
      "y": 53,
      "time_offset": 0.3796989917755127
    },
    {
      "x": 67,
      "y": 47,
      "time_offset": 0.38683295249938965
    },
    {
      "x": 66,
      "y": 42,
      "time_offset": 0.3935730457305908
    },
    {
      "x": 54,
      "y": 21,
      "time_offset": 0.4020380973815918
    },
    {
      "x": 53,
      "y": 19,
      "time_offset": 0.4069550037384033
    },
    {
      "x": 53,
      "y": 16,
      "time_offset": 0.4136466979980469
    },
    {
      "x": 53,
      "y": 15,
      "time_offset": 0.4204866886138916
    },
    {
      "x": 53,
      "y": 15,
      "time_offset": 0.4282996654510498
    },
    {
      "x": 53,
      "y": 14,
      "time_offset": 0.4340779781341553
    },
    {
      "x": 53,
      "y": 14,
      "time_offset": 0.46798253059387207
    },
    {
      "x": 53,
      "y": 13,
      "time_offset": 0.47482824325561523
    },
    {
      "x": 52,
      "y": 13,
      "time_offset": 0.48829126358032227
    },
    {
      "x": 51,
      "y": 12,
      "time_offset": 0.4955105781555176
    },
    {
      "x": 51,
      "y": 11,
      "time_offset": 0.5020778179168701
    },
    {
      "x": 50,
      "y": 11,
      "time_offset": 0.5083224773406982
    },
    {
      "x": 50,
      "y": 11,
      "time_offset": 0.515143871307373
    },
    {
      "x": 49,
      "y": 10,
      "time_offset": 0.5221450328826904
    },
    {
      "x": 49,
      "y": 9,
      "time_offset": 0.5355379581451416
    },
    {
      "x": 48,
      "y": 8,
      "time_offset": 0.5422711372375488
    },
    {
      "x": 48,
      "y": 7,
      "time_offset": 0.5491509437561035
    },
    {
      "x": 47,
      "y": 7,
      "time_offset": 0.5558321475982666
    },
    {
      "x": 46,
      "y": 6,
      "time_offset": 0.562117338180542
    },
    {
      "x": 46,
      "y": 5,
      "time_offset": 0.5692696571350098
    },
    {
      "x": 45,
      "y": 4,
      "time_offset": 0.5759897232055664
    },
    {
      "x": 45,
      "y": 2,
      "time_offset": 0.5824136734008789
    },
    {
      "x": 45,
      "y": 1,
      "time_offset": 0.5894501209259033
    },
    {
      "x": 45,
      "y": 0,
      "time_offset": 0.5958774089813232
    },
    {
      "x": 57,
      "y": 15,
      "time_offset": 0.6054434776306152
    },
    {
      "x": 56,
      "y": 15,
      "time_offset": 0.609605073928833
    },
    {
      "x": 56,
      "y": 14,
      "time_offset": 0.6163420677185059
    },
    {
      "x": 56,
      "y": 13,
      "time_offset": 0.629741907119751
    },
    {
      "x": 56,
      "y": 14,
      "time_offset": 0.6571905612945557
    },
    {
      "x": 56,
      "y": 14,
      "time_offset": 0.6710455417633057
    },
    {
      "x": 56,
      "y": 16,
      "time_offset": 0.6782219409942627
    },
    {
      "x": 44,
      "y": 1,
      "time_offset": 0.6860899925231934
    },
    {
      "x": 43,
      "y": 2,
      "time_offset": 0.6907815933227539
    },
    {
      "x": 43,
      "y": 3,
      "time_offset": 0.697209358215332
    },
    {
      "x": 43,
      "y": 5,
      "time_offset": 0.70428466796875
    },
    {
      "x": 43,
      "y": 6,
      "time_offset": 0.7117326259613037
    },
    {
      "x": 43,
      "y": 7,
      "time_offset": 0.7179150581359863
    },
    {
      "x": 42,
      "y": 9,
      "time_offset": 0.725332498550415
    },
    {
      "x": 42,
      "y": 10,
      "time_offset": 0.7311782836914062
    },
    {
      "x": 41,
      "y": 12,
      "time_offset": 0.7390663623809814
    },
    {
      "x": 41,
      "y": 13,
      "time_offset": 0.7453727722167969
    },
    {
      "x": 41,
      "y": 15,
      "time_offset": 0.7517743110656738
    },
    {
      "x": 41,
      "y": 16,
      "time_offset": 0.7583415508270264
    },
    {
      "x": 41,
      "y": 17,
      "time_offset": 0.76497483253479
    },
    {
      "x": 41,
      "y": 18,
      "time_offset": 0.7792763710021973
    },
    {
      "x": 41,
      "y": 18,
      "time_offset": 0.7850027084350586
    },
    {
      "x": 41,
      "y": 19,
      "time_offset": 0.8123490810394287
    }
  ],
  "timestamps": [
    1769737251.6123426,
    1769737251.6196353,
    1769737251.625732,
    1769737251.6321836,
    1769737251.639325,
    1769737251.6460285,
    1769737251.6522725,
    1769737251.6594596,
    1769737251.6662905,
    1769737251.6727488,
    1769737251.6796405,
    1769737251.686061,
    1769737251.6931949,
    1769737251.699935,
    1769737251.7084,
    1769737251.713317,
    1769737251.7200086,
    1769737251.7268486,
    1769737251.7346616,
    1769737251.74044,
    1769737251.7743444,
    1769737251.7811902,
    1769737251.7946532,
    1769737251.8018725,
    1769737251.8084397,
    1769737251.8146844,
    1769737251.8215058,
    1769737251.828507,
    1769737251.8418999,
    1769737251.848633,
    1769737251.8555129,
    1769737251.862194,
    1769737251.8684793,
    1769737251.8756316,
    1769737251.8823516,
    1769737251.8887756,
    1769737251.895812,
    1769737251.9022393,
    1769737251.9118054,
    1769737251.915967,
    1769737251.922704,
    1769737251.9361038,
    1769737251.9635525,
    1769737251.9774075,
    1769737251.9845839,
    1769737251.992452,
    1769737251.9971435,
    1769737252.0035713,
    1769737252.0106466,
    1769737252.0180945,
    1769737252.024277,
    1769737252.0316944,
    1769737252.0375402,
    1769737252.0454283,
    1769737252.0517347,
    1769737252.0581362,
    1769737252.0647035,
    1769737252.0713367,
    1769737252.0856383,
    1769737252.0913646,
    1769737252.118711
  ],
  "velocities": [
    1105.021967548406,
    919.8459064632482,
    956.4266104711284,
    31489.45404891546,
    1252.4620388340772,
    28044.965927550144,
    1368.3664548092825,
    1121.763473966482,
    1114.8953823956376,
    979.293697515865,
    1056.3548754254768,
    17384.565536481357,
    886.5419316325697,
    756.5206205143357,
    2857.250521564816,
    454.7713166027871,
    448.3169558556312,
    146.19903098748648,
    0.0,
    173.0609011388018,
    0.0,
    146.07682931076516,
    74.27753772047886,
    195.89305156921145,
    152.27097476856054,
    160.13683567501528,
    0.0,
    201.99698966510206,
    74.66628689429274,
    210.03652850521308,
    145.35292486831162,
    149.67362523641296,
    225.00726809482293,
    139.81479382646089,
    210.44637768806226,
    311.3349168646081,
    142.1171687053163,
    155.5866162178203,
    2008.0738928964593,
    240.2924090518476,
    148.43415790777507,
    74.62776008398129,
    36.43165867556112,
    0.0,
    278.69129568106314,
    2441.439617123258,
    301.4351865797196,
    155.57507418397626,
    282.67313654131283,
    134.26498927622524,
    161.74864062319233,
    301.4608615055536,
    171.06342020473917,
    283.4743497748006,
    158.5688253752221,
    312.4248789571695,
    152.27097476856054,
    150.75494213212565,
    69.92254730349254,
    0.0,
    36.56792125476247
  ],
  "accelerations": [
    -25391.81030841254,
    -25391.81030841254,
    -25391.81030841254,
    -25391.81030841254,
    6000.179623130433,
    4732623.766340607,
    -4234071.262840196,
    3996724.623197971,
    -4272395.581156779,
    -34311.755480540094,
    -1005.4400875347787,
    -20996.55527532377,
    11181.692615754413,
    2543186.872461261,
    -2312603.6494188784,
    -19290.728875431647,
    248165.0423009614,
    -488616.0180036396,
    -964.5331207196663,
    -44169.347859673006,
    -18712.333856177556,
    29950.075502974127,
    -5104.355863255284,
    21338.44006148642,
    -5333.074589401151,
    16845.85324299189,
    -6642.376155864121,
    1259.6140754194696,
    -23475.6761531949,
    28851.9251401429,
    -9507.310783537163,
    20104.951873858918,
    -9401.950979646186,
    646.6948876540317,
    11985.896349882421,
    -11911.168225397114,
    10510.549021395373,
    15705.06247856083,
    -24048.7472630878,
    2095.6657607940374,
    193651.89030038437,
    -424784.4714302716,
    -13634.902155451322,
    -5508.006149456961,
    -1391.5473292486827,
    -2629.499100177944,
    38834.41914419488,
    274877.2441931542,
    -456135.2344265924,
    -22692.197806450884,
    17963.603967435847,
    -19926.01830105144,
    4445.443244733696,
    18835.637777499003,
    -22306.232294864032,
    14250.736331855129,
    -19806.122286917307,
    24034.229458583843,
    -24386.791103790136,
    -228.54941237615515
  ],
  "click_data": {
    "time_to_click": 1.1158983707427979,
    "click_position": [
      41,
      19
    ],
    "click_timestamp": 1769737252.4222603
  },
  "total_time": 1.1158983707427979,
  "distance_traveled": 694.5194538966592,
  "metrics": {
    "total_time": 1.1158983707427979,
    "num_movements": 61,
    "total_distance": 694.5194538966592,
    "avg_velocity": 1690.34364695384,
    "max_velocity": 31489.45404891546,
    "avg_acceleration": -6224.809494431499,
    "max_acceleration": 4732623.766340607,
    "time_to_click": 1.1158983707427979
  }
}