{
  "session_id": "20260525_213248_455442",
  "session_user": [
    "DANIELA STEIM"
  ],
  "mouse_movements": [
    {
      "x": 119,
      "y": 53,
      "time_offset": 0.20453310012817383
    },
    {
      "x": 121,
      "y": 59,
      "time_offset": 0.21238470077514648
    },
    {
      "x": 125,
      "y": 66,
      "time_offset": 0.22038507461547852
    },
    {
      "x": 127,
      "y": 73,
      "time_offset": 0.22748351097106934
    },
    {
      "x": 84,
      "y": 12,
      "time_offset": 0.2430100440979004
    },
    {
      "x": 88,
      "y": 20,
      "time_offset": 0.250429630279541
    },
    {
      "x": 5,
      "y": 10,
      "time_offset": 0.26671314239501953
    },
    {
      "x": 9,
      "y": 16,
      "time_offset": 0.2725858688354492
    },
    {
      "x": 12,
      "y": 22,
      "time_offset": 0.28052568435668945
    },
    {
      "x": 16,
      "y": 27,
      "time_offset": 0.2884366512298584
    },
    {
      "x": 115,
      "y": 60,
      "time_offset": 0.30441856384277344
    },
    {
      "x": 117,
      "y": 64,
      "time_offset": 0.3127100467681885
    },
    {
      "x": 119,
      "y": 68,
      "time_offset": 0.3203709125518799
    },
    {
      "x": 121,
      "y": 73,
      "time_offset": 0.3284177780151367
    },
    {
      "x": 122,
      "y": 76,
      "time_offset": 0.3345906734466553
    },
    {
      "x": 122,
      "y": 80,
      "time_offset": 0.34321165084838867
    },
    {
      "x": 122,
      "y": 83,
      "time_offset": 0.35106897354125977
    },
    {
      "x": 123,
      "y": 85,
      "time_offset": 0.35915398597717285
    },
    {
      "x": 123,
      "y": 87,
      "time_offset": 0.3670222759246826
    },
    {
      "x": 123,
      "y": 89,
      "time_offset": 0.37519311904907227
    },
    {
      "x": 123,
      "y": 90,
      "time_offset": 0.3818502426147461
    },
    {
      "x": 123,
      "y": 91,
      "time_offset": 0.38922834396362305
    },
    {
      "x": 123,
      "y": 94,
      "time_offset": 0.3972597122192383
    },
    {
      "x": 123,
      "y": 97,
      "time_offset": 0.40512657165527344
    },
    {
      "x": 81,
      "y": 7,
      "time_offset": 0.42110753059387207
    },
    {
      "x": 81,
      "y": 11,
      "time_offset": 0.42705297470092773
    },
    {
      "x": 81,
      "y": 16,
      "time_offset": 0.4349849224090576
    },
    {
      "x": 69,
      "y": 9,
      "time_offset": 0.4511070251464844
    },
    {
      "x": 69,
      "y": 13,
      "time_offset": 0.459031343460083
    },
    {
      "x": 69,
      "y": 17,
      "time_offset": 0.4672970771789551
    },
    {
      "x": 69,
      "y": 20,
      "time_offset": 0.47318387031555176
    },
    {
      "x": 69,
      "y": 23,
      "time_offset": 0.4811561107635498
    },
    {
      "x": 69,
      "y": 26,
      "time_offset": 0.4891345500946045
    },
    {
      "x": 81,
      "y": 48,
      "time_offset": 0.5043549537658691
    },
    {
      "x": 81,
      "y": 51,
      "time_offset": 0.5106832981109619
    },
    {
      "x": 81,
      "y": 53,
      "time_offset": 0.5185525417327881
    },
    {
      "x": 81,
      "y": 55,
      "time_offset": 0.5265800952911377
    },
    {
      "x": 81,
      "y": 57,
      "time_offset": 0.534766674041748
    },
    {
      "x": 81,
      "y": 59,
      "time_offset": 0.5432894229888916
    },
    {
      "x": 81,
      "y": 60,
      "time_offset": 0.5505068302154541
    },
    {
      "x": 81,
      "y": 62,
      "time_offset": 0.5565412044525146
    },
    {
      "x": 123,
      "y": 164,
      "time_offset": 0.5725281238555908
    },
    {
      "x": 123,
      "y": 165,
      "time_offset": 0.5804080963134766
    },
    {
      "x": 121,
      "y": 164,
      "time_offset": 0.6859767436981201
    },
    {
      "x": 77,
      "y": 58,
      "time_offset": 0.6998558044433594
    },
    {
      "x": 73,
      "y": 53,
      "time_offset": 0.7076864242553711
    },
    {
      "x": 70,
      "y": 47,
      "time_offset": 0.715768575668335
    },
    {
      "x": 55,
      "y": 26,
      "time_offset": 0.732020378112793
    },
    {
      "x": 54,
      "y": 24,
      "time_offset": 0.7376742362976074
    },
    {
      "x": 52,
      "y": 22,
      "time_offset": 0.7458648681640625
    },
    {
      "x": 51,
      "y": 21,
      "time_offset": 0.7627906799316406
    },
    {
      "x": 50,
      "y": 20,
      "time_offset": 0.7778170108795166
    },
    {
      "x": 50,
      "y": 19,
      "time_offset": 0.791985034942627
    },
    {
      "x": 49,
      "y": 18,
      "time_offset": 0.7995738983154297
    },
    {
      "x": 48,
      "y": 17,
      "time_offset": 0.8068435192108154
    },
    {
      "x": 47,
      "y": 15,
      "time_offset": 0.8153321743011475
    },
    {
      "x": 46,
      "y": 13,
      "time_offset": 0.8213033676147461
    },
    {
      "x": 44,
      "y": 11,
      "time_offset": 0.8288509845733643
    },
    {
      "x": 43,
      "y": 9,
      "time_offset": 0.8363871574401855
    },
    {
      "x": 41,
      "y": 7,
      "time_offset": 0.8447058200836182
    },
    {
      "x": 40,
      "y": 6,
      "time_offset": 0.8523459434509277
    },
    {
      "x": 40,
      "y": 5,
      "time_offset": 0.8585436344146729
    },
    {
      "x": 39,
      "y": 5,
      "time_offset": 0.9202070236206055
    }
  ],
  "timestamps": [
    1779755568.6599681,
    1779755568.6678197,
    1779755568.67582,
    1779755568.6829185,
    1779755568.698445,
    1779755568.7058647,
    1779755568.7221482,
    1779755568.728021,
    1779755568.7359607,
    1779755568.7438717,
    1779755568.7598536,
    1779755568.768145,
    1779755568.775806,
    1779755568.7838528,
    1779755568.7900257,
    1779755568.7986467,
    1779755568.806504,
    1779755568.814589,
    1779755568.8224573,
    1779755568.8306282,
    1779755568.8372853,
    1779755568.8446634,
    1779755568.8526947,
    1779755568.8605616,
    1779755568.8765426,
    1779755568.882488,
    1779755568.89042,
    1779755568.906542,
    1779755568.9144664,
    1779755568.922732,
    1779755568.928619,
    1779755568.9365911,
    1779755568.9445696,
    1779755568.95979,
    1779755568.9661183,
    1779755568.9739876,
    1779755568.9820151,
    1779755568.9902017,
    1779755568.9987245,
    1779755569.0059419,
    1779755569.0119762,
    1779755569.0279632,
    1779755569.0358431,
    1779755569.1414118,
    1779755569.1552908,
    1779755569.1631215,
    1779755569.1712036,
    1779755569.1874554,
    1779755569.1931093,
    1779755569.2013,
    1779755569.2182257,
    1779755569.233252,
    1779755569.24742,
    1779755569.255009,
    1779755569.2622786,
    1779755569.2707672,
    1779755569.2767384,
    1779755569.284286,
    1779755569.2918222,
    1779755569.3001409,
    1779755569.307781,
    1779755569.3139787,
    1779755569.375642
  ],
  "velocities": [
    624.0434401689586,
    805.5115898915872,
    1007.7351270330074,
    1025.593458134848,
    4806.76735872289,
    1205.4947123777993,
    5134.042253368676,
    1227.8968932188789,
    844.8815862980553,
    809.3984389126773,
    6529.579113154877,
    539.3650321936498,
    583.7637783081836,
    669.2251575130656,
    512.2843396993115,
    463.98451284604107,
    381.80944289355506,
    276.56951615402903,
    254.18483728258894,
    244.7727816521257,
    150.21502757682114,
    135.53622439087442,
    373.535355934216,
    381.3465874651473,
    6214.75047430353,
    672.7840558206681,
    630.3621990441552,
    861.7017405055423,
    504.77528056082076,
    483.92558193198533,
    509.61532542221863,
    376.3057599138705,
    376.013387520918,
    1646.4693521627953,
    474.0576423162416,
    254.15403260013332,
    249.14190674190675,
    244.30229781285493,
    234.66606987998992,
    138.553911205074,
    331.43453180561045,
    6899.932068455667,
    126.90399685334786,
    21.18117483643214,
    8269.243574180358,
    817.7033735708667,
    830.0022592671712,
    1587.9454533935873,
    395.49417484605203,
    345.3246551502429,
    83.55366240584463,
    94.11569379636212,
    70.58147244425747,
    186.35380463448703,
    194.53745700422166,
    263.41840417647677,
    374.4758978757947,
    374.74439154156886,
    296.7113436774108,
    340.00983643436547,
    185.10349825294813,
    161.3504135410656,
    16.217078121677268
  ],
  "accelerations": [
    23112.249066385888,
    23112.249066385888,
    23112.249066385888,
    23112.249066385888,
    25276.760958588868,
    2515.811962979019,
    243529.82534484015,
    -485373.78745680593,
    241259.22670309822,
    -665133.2051257608,
    -48239.824451361426,
    -4485.311081977043,
    357915.9023569996,
    -722453.8885076919,
    5795.525906360463,
    10620.455827814085,
    -25424.182145127645,
    -5602.5929082657085,
    -10458.405892765866,
    -13016.66850530215,
    -2844.9229782799953,
    -1151.90751886652,
    -14203.995636024147,
    -1989.509562399957,
    29633.69677102546,
    992.9288294069376,
    365022.1434928431,
    -932136.6610622106,
    -5348.22698503577,
    14349.216428471356,
    -45041.913489544335,
    -2522.4256355164252,
    4363.962329596188,
    -16721.71911746895,
    -36.64531129721874,
    83470.58278358502,
    -185263.57699793694,
    -27944.694596337387,
    -624.3652965744915,
    -591.1637909414849,
    -1130.647868736606,
    -13316.715498772282,
    31963.64909155719,
    410866.99513767235,
    -859524.3330862575,
    -1001.4604206465812,
    594281.0216586987,
    -951590.0885877846,
    1521.7341358610238,
    46637.4850861469,
    -210909.3011477204,
    -6125.231912971147,
    -15465.78659499381,
    702.9015550872354,
    -1661.0799958606292,
    15255.55626750891,
    1125.733031681064,
    8114.471189989282,
    18598.87762240064,
    35.573303102983786,
    -10354.466284565458,
    5204.9824127845495
  ],
  "click_data": {
    "time_to_click": 1.0811750888824463,
    "click_position": [
      39,
      5
    ],
    "click_timestamp": 1779755569.5366101
  },
  "total_time": 1.0811750888824463,
  "distance_traveled": 829.7244076446295,
  "window_origin": {
    "x": 229,
    "y": 559
  },
  "metrics": {
    "total_time": 1.0811750888824463,
    "num_movements": 63,
    "total_distance": 829.7244076446295,
    "avg_velocity": 1033.7373618920697,
    "max_velocity": 8269.243574180358,
    "avg_acceleration": -43164.26917738965,
    "max_acceleration": 594281.0216586987,
    "time_to_click": 1.0811750888824463
  }
}